plugs_newsletter/__init__.py
plugs_newsletter/admin.py
plugs_newsletter/emails.py
plugs_newsletter/models.py
plugs_newsletter/runtests.py
plugs_newsletter/serializers.py
plugs_newsletter/settings.py
plugs_newsletter/signals.py
plugs_newsletter/urls.py
plugs_newsletter/views.py
plugs_newsletter/migrations/0001_initial.py
plugs_newsletter/migrations/0002_auto_20170829_1210.py
plugs_newsletter/migrations/__init__.py
plugs_newsletter/templates/emails/newsletter_subscribed_en.html
plugs_newsletter/templates/emails/newsletter_subscribed_pt.html
plugs_newsletter/templates/emails/newsletter_unsubscribed_en.html
plugs_newsletter/templates/emails/newsletter_unsubscribed_pt.html
plugs_newsletter/tests/__init__.py
plugs_newsletter/tests/test_serializers.py
plugs_newsletter/tests/test_settings.py
plugs_newsletter/tests/test_views.py
plugs_newsletter-0.2.0.dist-info/DESCRIPTION.rst
plugs_newsletter-0.2.0.dist-info/METADATA
plugs_newsletter-0.2.0.dist-info/RECORD
plugs_newsletter-0.2.0.dist-info/WHEEL
plugs_newsletter-0.2.0.dist-info/metadata.json
plugs_newsletter-0.2.0.dist-info/top_level.txt
